torchqf/__init__.py
torchqf/asset/__init__.py
torchqf/asset/derivative/__init__.py
torchqf/asset/derivative/option.py
torchqf/asset/primary/__init__.py
torchqf/autogreek.py
torchqf/functional.py
torchqf/model/__init__.py
torchqf/model/_utils.py
torchqf/model/bs.py
torchqf/model/factor_model.py
torchqf/stochastic/__init__.py
torchqf/stochastic/brownian.py
torchqf/tensor.py
torchqf-0.0.10.dist-info/LICENSE
torchqf-0.0.10.dist-info/WHEEL
torchqf-0.0.10.dist-info/METADATA
torchqf-0.0.10.dist-info/RECORD
