Metadata-Version: 2.1
Name: torchqf
Version: 0.0.10
Summary: PyTorch Quant Finance
Home-page: https://github.com/simaki/torchqf
License: BSD-3-Clause
Author: Shota Imaki
Author-email: shota.imaki.0801@gmail.com
Requires-Python: >=3.6.13,<4.0.0
Classifier: License :: OSI Approved :: BSD License
Classifier: Programming Language :: Python :: 3
Classifier: Programming Language :: Python :: 3.7
Classifier: Programming Language :: Python :: 3.8
Classifier: Programming Language :: Python :: 3.9
Requires-Dist: torch (>=1.8.1,<2.0.0)
Project-URL: Repository, https://github.com/simaki/torchqf
